NBCrawler/__init__.py
NBCrawler/main.py
NBCrawler/settings.py
NBCrawler/core/__init__.py
NBCrawler/core/requester.py
NBCrawler/core/utils.py
nbs/__init__.py
nbs/main.py
nbs/settings.py
nbs/core/__init__.py
nbs/core/requester.py
nbs/core/utils.py
nbs-0.0.9.dist-info/LICENSE.md
nbs-0.0.9.dist-info/METADATA
nbs-0.0.9.dist-info/WHEEL
nbs-0.0.9.dist-info/entry_points.txt
nbs-0.0.9.dist-info/top_level.txt
nbs-0.0.9.dist-info/RECORD
