Metadata-Version: 2.1
Name: nbs
Version: 0.0.9
Summary: Book information crawler using 'NAVER BOOKS API'
Home-page: https://github.com/jchrys/NBCrawler
Author: JCHRYS
Author-email: jchrys@me.com
License: UNKNOWN
Platform: UNKNOWN
Classifier: Programming Language :: Python :: 3
Classifier: License :: OSI Approved :: MIT License
Requires-Python: >=3.6
Requires-Dist: requests
Requires-Dist: bs4
Requires-Dist: tqdm
